tulipy/lib.cpython-36m-x86_64-linux-gnu.so
tulipy/__init__.py
newtulipy-0.4.6.dist-info/METADATA
newtulipy-0.4.6.dist-info/RECORD
newtulipy-0.4.6.dist-info/top_level.txt
newtulipy-0.4.6.dist-info/WHEEL
newtulipy-0.4.6.dist-info/LICENSE
newtulipy-0.4.6.dist-info/AUTHORS
