Metadata-Version: 2.1
Name: newtulipy
Version: 0.4.6
Summary: Financial Technical Analysis Indicator Library. Python bindings for https://github.com/TulipCharts/tulipindicators
Home-page: https://github.com/cryptocoinserver/tulipy
Author: https://travis-ci.org/cryptocoinserver/tulipy/blob/master/AUTHORS
License: LGPL-3.0
Platform: UNKNOWN
Classifier: Development Status :: 4 - Beta
Classifier: Intended Audience :: Developers
Classifier: Intended Audience :: Financial and Insurance Industry
Classifier: License :: OSI Approved :: GNU Lesser General Public License v3 (LGPLv3)
Classifier: Operating System :: OS Independent
Classifier: Programming Language :: Cython
Classifier: Programming Language :: Python :: 3
Classifier: Topic :: Office/Business :: Financial
Classifier: Topic :: Scientific/Engineering :: Information Analysis
